{
  "events": {
    "evt_tuborg_harbiye_1": {
      "translation": "与 Tuborg 一起迎接夏日",
      "sourceHash": "858675f4bf1a509b9785766fc6a4e1dd"
    },
    "evt_pepsi_istanbul_1": {
      "translation": "Pepsix 时刻",
      "sourceHash": "748d3591e6e27968a42396731adaff48"
    },
    "evt_pepsi_istanbul_2": {
      "translation": "百事可乐海滩清凉之旅",
      "sourceHash": "59548b630e9d936c27bc49e901f44d23"
    },
    "evt_tuborg_kadikoy_1": {
      "translation": "用 Tuborg 冷却",
      "sourceHash": "8018264e3adb2e01365321027fbf24ef"
    },
    "evt_tuborg_kadikoy_2": {
      "translation": "与 Tuborg 杯决赛",
      "sourceHash": "dd9fd8eb16639d723c71cb130f217a2f"
    }
  },
  "cameras": {
    "evt_tuborg_harbiye_1_camera": {
      "translation": "Tuborg 摄像机",
      "sourceHash": "8f45e3999a047e877e0849295ad9d474"
    },
    "evt_pepsi_istanbul_1_camera": {
      "translation": "Pepsix 能源相机",
      "sourceHash": "c1294f89bce0a4cfc47506a61e5e918f"
    },
    "evt_pepsi_istanbul_2_camera": {
      "translation": "Pepsix 夏季相机",
      "sourceHash": "dd0356ca5b055b305fa1fa92ae21ec26"
    },
    "evt_tuborg_kadikoy_1_camera": {
      "translation": "冰相机",
      "sourceHash": "a48577f8bf117b5500b3c764e108b8b5"
    },
    "evt_tuborg_kadikoy_2_camera": {
      "translation": "体育场摄像机",
      "sourceHash": "f5a1f77a7906c265284b56270de5acb4"
    }
  }
}